ej2_streamlit_grids/__init__.py
ej2_streamlit_grids/frontend/build/asset-manifest.json
ej2_streamlit_grids/frontend/build/index.html
ej2_streamlit_grids/frontend/build/precache-manifest.71f028053d48ce689f77c09b248f6e1a.js
ej2_streamlit_grids/frontend/build/service-worker.js
ej2_streamlit_grids/frontend/build/static/js/2.181e6ecb.chunk.js
ej2_streamlit_grids/frontend/build/static/js/2.181e6ecb.chunk.js.LICENSE.txt
ej2_streamlit_grids/frontend/build/static/js/2.181e6ecb.chunk.js.map
ej2_streamlit_grids/frontend/build/static/js/main.ed4cbcfc.chunk.js
ej2_streamlit_grids/frontend/build/static/js/main.ed4cbcfc.chunk.js.map
ej2_streamlit_grids/frontend/build/static/js/runtime-main.d4ad5a5b.js
ej2_streamlit_grids/frontend/build/static/js/runtime-main.d4ad5a5b.js.map
ej2_streamlit_grids-30.1.37.dist-info/METADATA
ej2_streamlit_grids-30.1.37.dist-info/WHEEL
ej2_streamlit_grids-30.1.37.dist-info/top_level.txt
ej2_streamlit_grids-30.1.37.dist-info/RECORD
