Metadata-Version: 2.4
Name: ej2_streamlit_grids
Version: 30.1.37
Summary: Streamlit component implementation of Syncfusion® Grid
Home-page: https://github.com/syncfusion/ej2-streamlit-components/tree/master/components/grids/src
Author: Syncfusion®
Author-email: info@syncfusion.com
Classifier: Programming Language :: Python :: 3
Classifier: Programming Language :: Python :: 3.8
Classifier: Programming Language :: Python :: 3.9
Classifier: Programming Language :: Python :: 3.10
Classifier: License :: OSI Approved :: MIT License
Classifier: Operating System :: OS Independent
Requires-Python: >=3.6
Requires-Dist: streamlit>=0.75
Dynamic: author
Dynamic: author-email
Dynamic: classifier
Dynamic: description
Dynamic: description-content-type
Dynamic: home-page
Dynamic: requires-dist
Dynamic: requires-python
Dynamic: summary
